cmethods/__init__.py
cmethods/_version.py
cmethods/core.py
cmethods/distribution.py
cmethods/scaling.py
cmethods/static.py
cmethods/types.py
cmethods/utils.py
python_cmethods-2.3.2.dist-info/licenses/LICENSE
python_cmethods-2.3.2.dist-info/METADATA
python_cmethods-2.3.2.dist-info/WHEEL
python_cmethods-2.3.2.dist-info/entry_points.txt
python_cmethods-2.3.2.dist-info/top_level.txt
python_cmethods-2.3.2.dist-info/RECORD
