Metadata-Version: 2.4
Name: python-cmethods
Version: 2.3.2
Summary: A collection of bias correction techniques written in Python - for climate sciences.
Author-email: Benjamin Thomas Schwertfeger <contact@b-schwertfeger.de>
Maintainer-email: Benjamin Thomas Schwertfeger <contact@b-schwertfeger.de>
License-Expression: GPL-3.0-or-later
Project-URL: Homepage, https://github.com/btschwertfeger/python-cmethods
Project-URL: Bug Tracker, https://github.com/btschwertfeger/python-cmethods/issues
Project-URL: Documentation, https://python-cmethods.readthedocs.io/en/stable/
Keywords: climate-science,bias,bias-correction,bias-adjustment,climate-reanalysis,reanalysis,linear-scaling,variance-scaling,delta-method,delta-change-method,quantile-mapping,quantile-delta-mapping
Classifier: Programming Language :: Python
Classifier: Programming Language :: Python :: 3.9
Classifier: Programming Language :: Python :: 3.10
Classifier: Programming Language :: Python :: 3.11
Classifier: Programming Language :: Python :: 3.12
Classifier: Programming Language :: Python :: 3.13
Classifier: Programming Language :: Python :: 3.14
Classifier: Topic :: Software Development :: Libraries :: Python Modules
Classifier: Topic :: Utilities
Classifier: Topic :: Scientific/Engineering
Classifier: Intended Audience :: Science/Research
Classifier: Natural Language :: English
Classifier: Operating System :: MacOS
Classifier: Operating System :: Unix
Requires-Python: >=3.9
License-File: LICENSE
Requires-Dist: xarray>=2022.11.0
Requires-Dist: netCDF4>=1.6.1
Requires-Dist: numpy
Requires-Dist: click~=8.1
Requires-Dist: cloup~=3.0
Dynamic: license-file
